[{"content": {"id": 101, "source": ["hospital ABC"], "dataset_type": "private", "dataset": "batch", "body_part": "LOW_EXM", "image_path": "gs://test-bucket-neu/sedi_xray/1.2.840.113845.11.1000000001951524609.20201001110828.1714272-1.2.392.200036.9125.3.331559710016.64951329144.2812692-1.2.392.200036.9125.4.0.521105724.1236410624.1637552228.dcm", "labels": [{"classification": "mass", "labelled_by": "Erick Silva", "labelled_date": "2020-09-15", "labelling_method": "ml_model", "classification_type": "binary", "value": false}, {"classification": "hernia", "labelled_by": "Ana Laura Oliveira", "labelled_date": "2020-12-09", "labelling_method": "ml_model", "classification_type": "binary", "value": true}, {"classification": "mass", "labelled_by": "Camila Pinto", "labelled_date": "2021-01-18", "labelling_method": "physician", "classification_type": "binary", "value": false}, {"classification": "tumor", "labelled_by": "Jo\u00e3o Guilherme Jesus", "labelled_date": "2020-08-24", "labelling_method": "physician", "classification_type": "binary", "value": true}, {"classification": "tumor", "labelled_by": "Daniela Nascimento", "labelled_date": "2021-08-01", "labelling_method": "physician", "classification_type": "binary", "value": false}, {"classification": "edema", "labelled_by": "Diego Nascimento", "labelled_date": "2021-08-09", "labelling_method": "physician", "classification_type": "binary", "value": true}, {"classification": "hernia", "labelled_by": "Catarina Nogueira", "labelled_date": "2020-05-21", "labelling_method": "physician", "classification_type": "binary", "value": false}]}, "publication_timestamp": 1626970521.528672}]